langchain_jenkins/__init__.py
langchain_jenkins/jenkins.py
langchain_jenkins/py.typed
langchain_jenkins/tools.py
langchain_jenkins-0.1.1.dist-info/LICENSE
langchain_jenkins-0.1.1.dist-info/METADATA
langchain_jenkins-0.1.1.dist-info/WHEEL
langchain_jenkins-0.1.1.dist-info/RECORD
