Metadata-Version: 2.1
Name: langchain-jenkins
Version: 0.1.1
Summary: An integration package connecting Jenkins and LangChain
Home-page: https://github.com/Amitgb14/langchain_jenkins
License: MIT
Requires-Python: >=3.9,<4.0
Classifier: License :: OSI Approved :: MIT License
Classifier: Programming Language :: Python :: 3
Classifier: Programming Language :: Python :: 3.9
Classifier: Programming Language :: Python :: 3.10
Classifier: Programming Language :: Python :: 3.11
Classifier: Programming Language :: Python :: 3.12
Classifier: Programming Language :: Python :: 3.13
Requires-Dist: langchain-core (>=0.3.15,<0.4.0)
Requires-Dist: python-jenkins (>=1.8.2,<2.0.0)
Project-URL: Repository, https://github.com/Amitgb14/langchain_jenkins
Project-URL: Release Notes, https://github.com/langchain-ai/langchain/releases?q=tag%3A%22jenkins%3D%3D0%22&expanded=true
Project-URL: Source Code, https://github.com/langchain-ai/langchain/tree/master/libs/partners/jenkins
